stack_dumpper
