Metadata-Version: 1.1
Name: stack-dumpper
Version: 0.0.2
Summary: Dump stack trace from all threads (including main thread) when CRTL + \ is pressed or SIGQUIT is received.
Home-page: https://github.com/jaysonsantos/python-stack-dumpper
Author: Jayson Reis
Author-email: santosdosreis@gmail.com
License: UNKNOWN
Platform: UNKNOWN
Classifier: Development Status :: 4 - Beta
Classifier: License :: OSI Approved :: MIT License
Classifier: Operating System :: OS Independent
Classifier: Programming Language :: Python :: 3.4
